setup.py
django_signals_ahoy.egg-info/PKG-INFO
django_signals_ahoy.egg-info/SOURCES.txt
django_signals_ahoy.egg-info/dependency_links.txt
django_signals_ahoy.egg-info/top_level.txt
signals_ahoy/__init__.py
signals_ahoy/asynchronous.py
signals_ahoy/signals.py
tests/__init__.py
tests/manage.py
tests/settings.py
tests/urls.py
tests/customapp/__init__.py
tests/customapp/listeners.py
tests/customapp/models.py
tests/customapp/signals.py
tests/customapp/urls.py
tests/customapp/views.py
tests/localsite/__init__.py
tests/localsite/forms.py
tests/localsite/listeners.py
tests/localsite/models.py
tests/localsite/urls.py
tests/localsite/views.py