Metadata-Version: 1.0
Name: django-signals-ahoy
Version: 0.1-3
Summary: signals-ahoy
Home-page: http://bitbucket.org/bkroeze/django-signals-ahoy/
Author: Bruce Kroeze
Author-email: brucek@ecomsmith.com
License: New BSD License
Platform: any
Classifier: Development Status :: 4 - Beta
Classifier: Environment :: Web Environment
Classifier: Intended Audience :: Developers
Classifier: License :: OSI Approved :: BSD License
Classifier: Operating System :: OS Independent
Classifier: Programming Language :: Python
Classifier: Framework :: Django
